segmentation_agent/__init__.py
segmentation_agent/agent.py
segmentation_agent/config.py
segmentation_agent/constants.py
segmentation_agent/models.py
segmentation_agent/utils.py
segmentation_agent-1.0.5.dist-info/METADATA
segmentation_agent-1.0.5.dist-info/WHEEL
segmentation_agent-1.0.5.dist-info/top_level.txt
segmentation_agent-1.0.5.dist-info/RECORD
