Metadata-Version: 2.4
Name: segmentation-agent
Version: 1.0.5
Summary: AI-powered dataset segmentation agent for ML workflows
Author-email: StepFunction AI <rajesh@stepfunction.ai>
Maintainer-email: StepFunction AI <rajesh@stepfunction.ai>
License: MIT
Project-URL: Homepage, https://github.com/stepfnAI/segmentation_agent
Project-URL: Documentation, https://github.com/stepfnAI/segmentation_agent#readme
Project-URL: Repository, https://github.com/stepfnAI/segmentation_agent.git
Project-URL: Bug Tracker, https://github.com/stepfnAI/segmentation_agent/issues
Keywords: machine learning,segmentation,AI,ML,automation,dataset segmentation
Classifier: Development Status :: 3 - Alpha
Classifier: Intended Audience :: Developers
Classifier: Intended Audience :: Science/Research
Classifier: License :: OSI Approved :: MIT License
Classifier: Programming Language :: Python :: 3
Classifier: Programming Language :: Python :: 3.9
Classifier: Programming Language :: Python :: 3.10
Classifier: Programming Language :: Python :: 3.11
Classifier: Topic :: Scientific/Engineering :: Artificial Intelligence
Classifier: Topic :: Scientific/Engineering :: Information Analysis
Requires-Python: >=3.10
Requires-Dist: sfn-blueprint>=0.6.15
Requires-Dist: sfn-db-query-builder>=0.1.0
Requires-Dist: pandas>=1.5.0
Requires-Dist: numpy>=1.21.0
Requires-Dist: pydantic>=2.0.0
Requires-Dist: pydantic-settings>=2.0.0
Requires-Dist: sqlalchemy>=2.0.0
Provides-Extra: dev
Requires-Dist: pytest>=7.0.0; extra == "dev"
Requires-Dist: pytest-cov>=4.0.0; extra == "dev"
Requires-Dist: pytest-asyncio>=0.20.0; extra == "dev"
Requires-Dist: black>=22.0.0; extra == "dev"
Requires-Dist: flake8>=5.0.0; extra == "dev"
Requires-Dist: mypy>=1.0.0; extra == "dev"
Provides-Extra: test
Requires-Dist: pytest>=7.0.0; extra == "test"
Requires-Dist: pytest-cov>=4.0.0; extra == "test"
Requires-Dist: pytest-asyncio>=0.20.0; extra == "test"
